nazgul/__init__.py
nazgul/_version.py
nazgul/fit.py
nazgul/nazgul.py
nazgul/versioneer.py
nazgul/stan_models/__init__.py
nazgul/stan_models/amplitude_parameters.stan
nazgul/stan_models/amplitude_priors.stan
nazgul/stan_models/amplitude_transformed_parameters.stan
nazgul/stan_models/data.stan
nazgul/stan_models/ea_earth_amp.stan
nazgul/stan_models/ea_earth_parameter_ops.stan
nazgul/stan_models/earth_occ_amp.stan
nazgul/stan_models/earth_occ_parameter_ops.stan
nazgul/stan_models/earth_occ_parameters.stan
nazgul/stan_models/earth_occ_transform_data.stan
nazgul/stan_models/earth_occ_transform_data_ops.stan
nazgul/stan_models/effective_area_amp.stan
nazgul/stan_models/effective_area_model_dec.stan
nazgul/stan_models/effective_area_parameter_ops.stan
nazgul/stan_models/effective_area_parameters.stan
nazgul/stan_models/functions.stan
nazgul/stan_models/know_effective_area_data.stan
nazgul/stan_models/known_effective_area_model.stan
nazgul/stan_models/known_effective_area_transformed_data.stan
nazgul/stan_models/nazgul_ea_earth.stan
nazgul/stan_models/nazgul_earth_occ.stan
nazgul/stan_models/nazgul_effective_area.stan
nazgul/stan_models/nazgul_known_effective_area.stan
nazgul/stan_models/nazgul_standard.stan
nazgul/stan_models/rff.stan
nazgul/stan_models/rff_bw.stan
nazgul/stan_models/rff_bw_ipn.stan
nazgul/stan_models/rff_ipn.stan
nazgul/stan_models/rff_omega.stan
nazgul/stan_models/rff_omega_ipn_cos.stan
nazgul/stan_models/rff_omega_ipn_earth.stan
nazgul/stan_models/stan_models.py
nazgul/stan_models/standard_amp.stan
nazgul/stan_models/standard_likelihood.stan
nazgul/stan_models/standard_model_dec.stan
nazgul/stan_models/standard_parameters.stan
nazgul/stan_models/standard_priors.stan
nazgul/stan_models/standard_trans_data_ops.stan
nazgul/stan_models/standard_transformed_parameter_ops.stan
nazgul/stan_models/standard_transformed_parameters.stan
nazgul/stan_models/transform_data.stan
nazgul-0.1.1.dist-info/LICENSE
nazgul-0.1.1.dist-info/METADATA
nazgul-0.1.1.dist-info/WHEEL
nazgul-0.1.1.dist-info/top_level.txt
nazgul-0.1.1.dist-info/RECORD
