Metadata-Version: 2.1
Name: nazgul
Version: 0.1.1
Summary: A code for fitting random Fourier features to time-seires for the IPN
Home-page: https://github.com/grburgessp/nazgul
Author: J. Michael Burgess
Author-email: jmichaelburgess@gmail.com
License: GPL-3
Project-URL: Bug Tracker, https://github.com/grburgessp/nazgul/issues
Project-URL: Source Code, https://github.com/grburgessp/nazgul
Platform: UNKNOWN
Classifier: Development Status :: 2 - Pre-Alpha
Classifier: Environment :: Console
Classifier: Intended Audience :: Science/Research
Classifier: License :: OSI Approved :: GNU General Public License v3 (GPLv3)
Classifier: Operating System :: POSIX
Classifier: Programming Language :: Python :: 3.5
Classifier: Programming Language :: Python :: 3.6
Classifier: Programming Language :: Python :: 3.7
Classifier: Programming Language :: Python :: 3.8
Classifier: Topic :: Scientific/Engineering :: Physics
Requires-Dist: numpy
Requires-Dist: scipy
Requires-Dist: ipython
Requires-Dist: matplotlib
Requires-Dist: mpltools
Requires-Dist: astropy
Requires-Dist: pyipn
Requires-Dist: ipyvolume (>=0.6.0a2)
Requires-Dist: pythreejs
Requires-Dist: numba
Requires-Dist: pandas
Requires-Dist: pyyaml
Requires-Dist: reproject
Requires-Dist: pyorbital
Requires-Dist: cmdstanpy
Requires-Dist: arviz
Requires-Dist: astropy-healpix
Requires-Dist: mocpy
Requires-Dist: ligo.skymap
Requires-Dist: networkx (==2.3)
